{
    "Python":{
        "caption":"Learn Python since 2016, but start using them on 2018",
        "year_exp":4,
        "modules":[
            "Django",
            "Flask",
            "Requests",
            "Pandas",
            "Matplotlib",
            "Pywin32",
            "Dash",
            "Eel",
            "Tkinter",
            "PyODBC",
            "Google API",
            "Openpyxl",
            "XlWings"
        ]
    },
    "Javascript":{  
        "caption":"Seems like all those pretty & interactive things is developed in Javascript, so I learn them.",
        "year_exp":3,
        "modules":[
            "ReactJS",
            "React Hooks",
            "Redux",
            "NodeJS",
            "Axios",
            "Vanilla",
            "Web Component",
            "Lit-Element",
            "ElectronJS",
            "ExcelJS",
            "SpreadSheetJS",
            "ChartJS",
            "CKEditor"
        ]
    },
    "CSS & Design Tool":{
        "caption":"Basic Stuff",
        "year_exp":5,
        "modules":[
            "CSS Grid",
            "CSS Flexbox",
            "CSS Media Query",
            "CSS Animation",
            "React-Icons"
        ]        
    },
    
    "DevOps":{
        "caption":"Data has to sit somewhere right, local file-based data storage is not the right place.",
        "year_exp":2,
        "modules":[
            "Postgres",
            "MS SQL",
            "AWS EC2",
            "Heroku",
            "Linux Ubuntu",
            "NGINX",
            "GIT",
            "JIRA",
            "Confluence"
        ]
    },
    "Others":{
        "caption":"The quick tools for prototyping, automation, visualization, project management & documentation",
        "year_exp": 6,
        "modules":[
            "Excel",
            "Excel VBA",
            "Power BI",
            "Tableau",
            "Access",
            "Sharepoint",
            "Task Scheduler"
        ]
    },
    "Mechanical Engineering":{
        "caption":"Graduated as Mechanical Engineering, pretty enjoyful but not the main focus at the moment",
        "year_exp": 6,
        "modules":[
            "Mechanical Vibration & Acoustics",
            "Fluid Dynamics",
            "Thermodynamics",
            "Component Design",
            "CAD Modelling",
            "Mechatronics",
            "Failure Analysis",
            "Material Science",
            "Finite Element Analysis"
        ]
    }
}
